biodbs/BioMart.py
biodbs/HPA.py
biodbs/KEGG.py
biodbs/QuickGO.py
biodbs/__init__.py
biodbs/utils.py
biodbs-0.0.1.dist-info/METADATA
biodbs-0.0.1.dist-info/WHEEL
biodbs-0.0.1.dist-info/top_level.txt
biodbs-0.0.1.dist-info/RECORD
