Metadata-Version: 2.1
Name: biodbs
Version: 0.0.1
Summary: bioDBs is a Python package for getting data from biological databases.
Home-page: https://github.com/qwerty239qwe/biodbs
Author: qwerty239qwe
Author-email: qwerty239qwe@gmail.com
License: MIT
Platform: UNKNOWN
Classifier: License :: OSI Approved :: MIT License
Classifier: Programming Language :: Python :: 3
Classifier: Programming Language :: Python :: 3.7
Requires-Dist: pandas
Requires-Dist: tqdm
Requires-Dist: aiohttp
Requires-Dist: requests
